{
	"textures": {
		"1": "animated_java:item/demo_title/soul_destroyers"
	},
	"elements": [
		{
			"from": [
				-15.272727272727273,
				8.727272727272727,
				4
			],
			"to": [
				-5.09090909090909,
				23.272727272727273,
				12
			],
			"faces": {
				"north": {
					"uv": [
						8.8,
						1.1,
						9.248,
						3.1
					],
					"texture": "#1"
				},
				"south": {
					"uv": [
						9.248,
						1.1,
						8.8,
						3.1
					],
					"texture": "#1"
				},
				"up": {
					"uv": [
						9.248,
						1.1,
						8.8,
						0
					],
					"texture": "#1"
				},
				"down": {
					"uv": [
						9.248,
						4.2,
						8.8,
						3.1
					],
					"texture": "#1"
				}
			}
		},
		{
			"from": [
				-4.363636363636365,
				24,
				12.727272727272727
			],
			"to": [
				-16,
				8,
				3.2727272727272725
			],
			"faces": {
				"north": {
					"uv": [
						0,
						13.3,
						0.016,
						13.350000000000001
					],
					"texture": "#1"
				},
				"east": {
					"uv": [
						0,
						13.3,
						0.016,
						13.350000000000001
					],
					"texture": "#1"
				},
				"south": {
					"uv": [
						0,
						13.3,
						0.016,
						13.350000000000001
					],
					"texture": "#1"
				},
				"west": {
					"uv": [
						0,
						13.3,
						0.016,
						13.350000000000001
					],
					"texture": "#1"
				},
				"up": {
					"uv": [
						0,
						13.3,
						0.016,
						13.350000000000001
					],
					"texture": "#1"
				},
				"down": {
					"uv": [
						0,
						13.3,
						0.016,
						13.350000000000001
					],
					"texture": "#1"
				}
			}
		}
	],
	"display": {
		"head": {
			"rotation": [
				0,
				180,
				0
			]
		}
	}
}